package1/__init__.py
package2/__init__.py
package3/__init__.py
Mypackage_665-0.0.0.dist-info/METADATA
Mypackage_665-0.0.0.dist-info/WHEEL
Mypackage_665-0.0.0.dist-info/top_level.txt
Mypackage_665-0.0.0.dist-info/RECORD
