Metadata-Version: 2.1
Name: Mypackage-665
Version: 0.0.0
Summary: This is my package
Home-page: UNKNOWN
Author: me
License: UNKNOWN
Platform: UNKNOWN
